{
  "type": "malum:spirit_infusion",
  "spirits": [
    {
      "type": "wicked",
      "count": 12
    },
    {
      "type": "aerial",
      "count": 4
    }
  ],
  "ingredient": {
    "item": "minecraft:book"
  },
  "extraIngredients": [
    {
      "item": "malum:astral_weave"
    },
    {
      "item": "minecraft:lapis_lazuli",
      "count": 2
    },
    {
      "item": "minecraft:amethyst_shard",
      "count": 2
    }
  ],
  "output": {
    "count": 1,
    "id": "minecraft:enchanted_book",
    "components": {
      "minecraft:stored_enchantments": {
        "levels": {
          "minecraft:sweeping_edge": 2
        }
      }
    }
  }
}